s1swotcolocs/__init__.py
s1swotcolocs/check_lonlat_polygon_extent.py
s1swotcolocs/coloc_SWOT_L3_with_S1_CDSE_TOPS.py
s1swotcolocs/coloc_SWOT_L3_with_S1_CDSE_TOPS_sequential_wrapper.py
s1swotcolocs/coloc_SWOT_L3_with_S1_CDSE_TOPS_sequentiel.py
s1swotcolocs/config.yml
s1swotcolocs/illustrate_coloc_swh_file.py
s1swotcolocs/illustrate_coloc_swh_file_pyplot.py
s1swotcolocs/pickup_best_swot_file.py
s1swotcolocs/seastate_colocs_s1_swot.py
s1swotcolocs/seastate_colocs_s1_swot_sequential.py
s1swotcolocs/seastate_colocs_s1_swot_sequential_wrapper.py
s1swotcolocs/utils.py
s1swotcolocs/assets/SWOT_L3_LR_SSH_Expert_026_165_20241229T165806_20241229T174933_v2.0.1.nc
s1swotcolocs/assets/seastate_coloc_S1A_IW_SLC__1SDV_20240729T172527_20240729T172557_054978_06B28F_CEF7-iw3_SWOT_L3_Sentinel-1_IW_20240729T172147.nc
s1swotcolocs-2025.9.10.post1.dist-info/licenses/AUTHORS.rst
s1swotcolocs-2025.9.10.post1.dist-info/licenses/LICENSE
s1swotcolocs-2025.9.10.post1.dist-info/METADATA
s1swotcolocs-2025.9.10.post1.dist-info/WHEEL
s1swotcolocs-2025.9.10.post1.dist-info/entry_points.txt
s1swotcolocs-2025.9.10.post1.dist-info/top_level.txt
s1swotcolocs-2025.9.10.post1.dist-info/RECORD
