Metadata-Version: 2.4
Name: s1swotcolocs
Version: 2025.9.10.post1
Summary: Python lib to create co-locations between Sentinel-1 IW or EW images and SWOT KaRin swath.
Author: Antoine Grouazel
License: MIT
Project-URL: bugs, https://github.com/agrouaze/s1swotcolocs/issues
Project-URL: changelog, https://github.com/agrouaze/s1swotcolocs/blob/master/changelog.md
Project-URL: homepage, https://github.com/agrouaze/s1swotcolocs
Keywords: SAR,SWOT,colocations,sea-state
Classifier: Programming Language :: Python :: 3
Requires-Python: >=3.9
License-File: LICENSE
License-File: AUTHORS.rst
Requires-Dist: numpy
Requires-Dist: scipy
Requires-Dist: pandas
Requires-Dist: xarray
Requires-Dist: antimeridian
Requires-Dist: shapely
Requires-Dist: tqdm
Requires-Dist: geopandas
Requires-Dist: geodatasets
Requires-Dist: cdsodatacli
Requires-Dist: h5netcdf
Requires-Dist: alphashape
Requires-Dist: geoviews
Requires-Dist: hvplot
Dynamic: license-file
